{
"type": "FeatureCollection",
"crs": { "type": "name", "properties": { "name": "urn:ogc:def:crs:EPSG::6668" } },
"features": [
{ "type": "Feature", "properties": { "観測項目": "水位流量", "水系名": "鶴見川", "河川名": "鶴見川", "観測所名": "鶴見川河口", "所在地": "神奈川県横浜市鶴見区末広町", "観測所記号": "303061283310010", "lon": 139.68416666666667, "lat": 35.479444444444447, "最新の零点高": "T.P. 0.000m" }, "geometry": { "type": "Point", "coordinates": [ 139.68416666666667, 35.479444444444447 ] } },
{ "type": "Feature", "properties": { "観測項目": "水位流量", "水系名": "鶴見川", "河川名": "鶴見川", "観測所名": "芦穂橋", "所在地": "神奈川県横浜市鶴見区鶴見中央", "観測所記号": "303061283310020", "lon": 139.68555555555557, "lat": 35.50611111111111, "最新の零点高": "T.P. 0.000m" }, "geometry": { "type": "Point", "coordinates": [ 139.685555555555567, 35.50611111111111 ] } },
{ "type": "Feature", "properties": { "観測項目": "水位流量", "水系名": "鶴見川", "河川名": "鶴見川", "観測所名": "末吉橋", "所在地": "神奈川県川崎市幸区小倉", "観測所記号": "303061283310030", "lon": 139.66611111111112, "lat": 35.534444444444439, "最新の零点高": "T.P. 0.000m" }, "geometry": { "type": "Point", "coordinates": [ 139.666111111111121, 35.534444444444439 ] } },
{ "type": "Feature", "properties": { "観測項目": "水位流量", "水系名": "鶴見川", "河川名": "鶴見川", "観測所名": "綱島", "所在地": "神奈川県横浜市港北区綱島東", "観測所記号": "303061283310040", "lon": 139.63555555555556, "lat": 35.534444444444439, "最新の零点高": "T.P. 0.000m" }, "geometry": { "type": "Point", "coordinates": [ 139.635555555555555, 35.534444444444439 ] } },
{ "type": "Feature", "properties": { "観測項目": "水位流量", "水系名": "鶴見川", "河川名": "鶴見川", "観測所名": "太尾", "所在地": "神奈川県横浜市港北区太尾町", "観測所記号": "303061283310050", "lon": 139.61805555555557, "lat": 35.531388888888891, "最新の零点高": "T.P. 0.000m" }, "geometry": { "type": "Point", "coordinates": [ 139.618055555555571, 35.531388888888891 ] } },
{ "type": "Feature", "properties": { "観測項目": "水位流量", "水系名": "鶴見川", "河川名": "鶴見川", "観測所名": "亀の子橋", "所在地": "神奈川県横浜市港北区小机町", "観測所記号": "303061283310060", "lon": 139.60888888888888, "lat": 35.515, "最新の零点高": "T.P. 0.000m" }, "geometry": { "type": "Point", "coordinates": [ 139.608888888888885, 35.515 ] } },
{ "type": "Feature", "properties": { "観測項目": "水位流量", "水系名": "鶴見川", "河川名": "鶴見川", "観測所名": "落合橋", "所在地": "神奈川県横浜市緑区中山", "観測所記号": "303061283310070", "lon": 139.55194444444444, "lat": 35.513333333333335, "最新の零点高": "T.P. 5.890m" }, "geometry": { "type": "Point", "coordinates": [ 139.551944444444445, 35.513333333333335 ] } },
{ "type": "Feature", "properties": { "観測項目": "水位流量", "水系名": "鶴見川", "河川名": "矢上川", "観測所名": "矢上橋", "所在地": "神奈川県川崎市幸区南加瀬", "観測所記号": "303061283310080", "lon": 139.6575, "lat": 35.551111111111105, "最新の零点高": "T.P. 0.000m" }, "geometry": { "type": "Point", "coordinates": [ 139.6575, 35.551111111111105 ] } },
{ "type": "Feature", "properties": { "観測項目": "水位流量", "水系名": "鶴見川", "河川名": "早淵川", "観測所名": "高田橋", "所在地": "神奈川県横浜市港北区新吉田町", "観測所記号": "303061283310090", "lon": 139.62055555555557, "lat": 35.547222222222217, "最新の零点高": "T.P. 2.000m" }, "geometry": { "type": "Point", "coordinates": [ 139.620555555555569, 35.547222222222217 ] } },
{ "type": "Feature", "properties": { "観測項目": "水位流量", "水系名": "鶴見川", "河川名": "鳥山川", "観測所名": "鳥山", "所在地": "神奈川県横浜市港北区小机町", "観測所記号": "303061283310100", "lon": 139.60694444444445, "lat": 35.50277777777778, "最新の零点高": "T.P. 4.600m" }, "geometry": { "type": "Point", "coordinates": [ 139.606944444444451, 35.50277777777778 ] } },
{ "type": "Feature", "properties": { "観測項目": "水位流量", "水系名": "鶴見川", "河川名": "恩田川", "観測所名": "浅山橋", "所在地": "神奈川県横浜市緑区長津田", "観測所記号": "303061283310110", "lon": 139.49833333333331, "lat": 35.536944444444444, "最新の零点高": "T.P. 21.000m" }, "geometry": { "type": "Point", "coordinates": [ 139.498333333333306, 35.536944444444444 ] } },
{ "type": "Feature", "properties": { "観測項目": "水位流量", "水系名": "鶴見川", "河川名": "谷本川", "観測所名": "寺家橋", "所在地": "神奈川県川崎市麻生区早野字広地", "観測所記号": "303061283310120", "lon": 139.51222222222222, "lat": 35.569722222222225, "最新の零点高": "T.P. 19.000m" }, "geometry": { "type": "Point", "coordinates": [ 139.512222222222221, 35.569722222222225 ] } }
]
}
